tests/__init__.py
tests/test_autoencoder.py
tests/test_classification.py
tests/test_layers.py
tests/test_models.py
tests/test_state.py
tests/test_trainer.py
tests/test_transforms.py
torchfuel/__init__.py
torchfuel/data_loaders/__init__.py
torchfuel/data_loaders/image.py
torchfuel/layers/__init__.py
torchfuel/layers/utils.py
torchfuel/models/__init__.py
torchfuel/models/cam_resnet.py
torchfuel/trainers/__init__.py
torchfuel/trainers/classification.py
torchfuel/trainers/const.py
torchfuel/trainers/generic.py
torchfuel/trainers/mse.py
torchfuel/trainers/state.py
torchfuel/trainers/hooks/__init__.py
torchfuel/trainers/hooks/generic.py
torchfuel/trainers/hooks/metrics.py
torchfuel/transforms/__init__.py
torchfuel/transforms/noise.py
torchfuel/utils/__init__.py
torchfuel/utils/time_parser.py
torchfuel-0.1.3.dist-info/LICENCE
torchfuel-0.1.3.dist-info/METADATA
torchfuel-0.1.3.dist-info/WHEEL
torchfuel-0.1.3.dist-info/top_level.txt
torchfuel-0.1.3.dist-info/RECORD
