Metadata-Version: 2.1
Name: torchfuel
Version: 0.1.3
Summary: Library build on top of pytorch to fuel productivity
Home-page: https://github.com/vturrisi/torchfuel
Author: Victor Turrisi
Author-email: vt.turrisi@gmail.com
License: MIT
Platform: UNKNOWN
Classifier: Programming Language :: Python :: 3
Classifier: License :: OSI Approved :: MIT License
Classifier: Operating System :: OS Independent
Requires-Dist: torch
Requires-Dist: torchvision
Requires-Dist: tqdm
